{"spring_24.md":"DKLhVoHN","spring_18.md":"CQ_A2IQy","spring_1.md":"SSWvkEY5","javaview_4.md":"CSEllisV","spring_19.md":"CMLNv_pL","spring_20.md":"DCUPeCyM","spring_21.md":"DDkPqDDi","spring_2.md":"Thmui85d","spring_23.md":"D10Gue3e","spring_22.md":"B9QrH0MG","spring_25.md":"Bon2fsqC","spring_14.md":"Ds9shEd2","spring_13.md":"D0_w_qCQ","spring_27.md":"Cn7Wf66g","spring_3.md":"BGvBg6mV","spring_26.md":"19PNVWSo","spring_8.md":"Dsn0y_Ql","spring_7.md":"BrcDrg_7","spring_5.md":"CkRPqkAl","spring_28.md":"Bm6gcZ4r","spring_6.md":"DJwWH3Gb","spring_10.md":"DmmgRW_L","thinkinginjava_2.md":"Dpor4cga","javaview_1.md":"CNRDL0B8","spring_15.md":"B50cnp9Z","spring_17.md":"Bi64d--7","spring_4.md":"CSgRQNzT","spring_9.md":"ChYDKx9l","thinkinginjava_1.md":"B3BGk7Fh","thinkinginjava_10.md":"D2diIFUW","thinkinginjava_3.md":"CFxt3fPx","thinkinginjava_6.md":"CCS4Cu8b","thinkinginjava_8.md":"DD1bcXEY","thinkinginjava_7.md":"BMiPMiRu","javaview_2.md":"B0obkIq9","spring_16.md":"ZZ1E8di0","thinkinginjava_9.md":"DY2gHBAl","thinkinginjava_index.md":"bYE-YM2e","changelog.md":"Pv0r7n1S","javaview_3.md":"jc-A8ma_","thinkinginjava_5.md":"sCKWlZKP","spring_12.md":"DVkw2Ukf","thinkinginjava_4.md":"CpcJNR4Q","assets.md":"Bpn_7Vjn","spring_11.md":"DUTU96qj","fr_index.md":"C8w3fTXQ","en_index.md":"CYbwVK-O","configuration.md":"Cb1Mxzzf","java_annotation.md":"DRaVCYFG","getting-started.md":"D__4wC9O","components.md":"CG2Y4Elj","java_t.md":"P3tNcQC0","index.md":"B55t4dyP","java_inference.md":"Bfrl1oFc","java_by.md":"DJd2gHN6","java_key-value.md":"D2iIwvVS","java_exception.md":"BaoNeaRW","java_data-types.md":"DAEJALJC","java_object.md":"BPIeUQP4","java_reflection.md":"DGx-YtjM","frontmatter.md":"CfG00vlJ","java_extend.md":"BMlc97_Y","javaconcurrency_juc-aqs.md":"ChBpgFUC","javaconcurrency_interrupt.md":"Bce3o2Pb","javaconcurrency_examplethread.md":"4fiRXjOP","java_string.md":"DV4ao-u0","javaconcurrency_basicthreading.md":"Dtic_bgX","javaconcurrency_multithreaded.md":"9nCk2HTP","javaconcurrency_threadstate.md":"eelefcAO","javaconcurrency_lockoptimization.md":"CTPHsUk7","javaconcurrency_threadsafety.md":"BLq3bZSz","javaconcurrency_usethread.md":"Kqbw-VFE","javaconcurrency_juc-other.md":"B3RYQh9B","javaconcurrency_exclusivesynchronization.md":"DhvxJlSa","javaconcurrency_collaborationthreads.md":"-vDjU86N","javaconcurrency_memorymodel.md":"CvN6Zc1I","javacontainer_design.md":"BrgPh4Y4","javacontainer_overview.md":"BxHhBavC","javaio_byteoperation.md":"D9MfWCLb","javaio_diskoperation.md":"ClFn7cfS","javaio_characteroperation.md":"CRrjKHux","javacontainer_codeanalysis.md":"DFus7MAX","javavirtual_runtimedataarea.md":"ChBrU2rH","javavirtual_memoryallocationandreclamationpolicy.md":"jpnp9igu","javaio_overview.md":"hlPNk1Jo","javaio_nio.md":"CWKTWn7O","javaio_objectoperation.md":"CsjTXpyp","javaio_networkoperation.md":"Dji_B2xK","kafka-study_1.md":"-dQQxfSq","javavirtual_refusecollection.md":"BjH3ZBaY","javavirtual_classloadingmechanism.md":"DMbU9obx","kafka-study_3.md":"iLTN_frm","kafka-study_2.md":"Bf1uXZjL","kafka-study_4.md":"1EUSrjyi","nav_ahua.md":"DI38h0DG","layout.md":"trSingjK","markdown.md":"DPI7jcSx","nav_mao.md":"ESJKdT3Y","nginx-tutorial_nginx-faq.md":"BnuVBBlr","nginx-tutorial_nginx-ops.md":"C7z1U2Ls","preface.md":"BKJVSaUT","soft_kafka.md":"DkXvOwOA","soft_elastic.md":"C043WP8M","soft_nacos.md":"dvHWUcKJ","nginx-tutorial_nginx-quickstart.md":"ClkhxVGf","soft_gitlab.md":"CPdL3ora","soft_jenkins.md":"B6Ez40G7","page.md":"CocovBms","soft_svn.md":"D1cUznCP","soft_nodejs.md":"DMdZL-pq","soft_jdk.md":"BjglWwj0","soft_maven.md":"CFo2xCdP","soft_tomcat.md":"DQCuh_13","plugin.md":"D4XwQTZT","soft_yapi.md":"BulJk7fK","soft_rocketmq.md":"BycBZSmD","soft_emqx.md":"EMfsvVN2","soft_nexus.md":"CKHgGu2_","team.md":"DffWy6Ys","update.md":"B1nz36gz","nginx-tutorial_nginx-configuration.md":"Bc_NgwTc","nav_index.md":"Cu5tzG-3","style.md":"BRTxWiHT"}
